wcpan/worker/__init__.py
wcpan/worker/aioqueue.py
wcpan/worker/queue.py
wcpan/worker/task.py
wcpan_worker-6.1.1.dist-info/LICENSE.txt
wcpan_worker-6.1.1.dist-info/METADATA
wcpan_worker-6.1.1.dist-info/WHEEL
wcpan_worker-6.1.1.dist-info/RECORD
